iot/storage/client/__init__.py
iot/storage/client/_aioclient.py
iot/storage/client/_client.py
iot/storage/client/_helpers.py
iot/storage/client/_types.py
iot/storage/client/_version.py
iot_storage_client-1.2.2.dist-info/METADATA
iot_storage_client-1.2.2.dist-info/WHEEL
iot_storage_client-1.2.2.dist-info/top_level.txt
iot_storage_client-1.2.2.dist-info/RECORD
