Metadata-Version: 2.1
Name: iot-storage-client
Version: 1.2.2
Summary: IoT Storage Client Library for Python
Author: Dylan Gonzales
Author-email: py.iot.utils@gmail.com
License: MIT License
Classifier: Programming Language :: Python :: 3 :: Only
Classifier: Programming Language :: Python :: 3
Classifier: Programming Language :: Python :: 3.7
Classifier: Programming Language :: Python :: 3.8
Classifier: Programming Language :: Python :: 3.9
Classifier: Programming Language :: Python :: 3.10
Classifier: License :: OSI Approved :: MIT License
Requires-Python: >=3.7
Requires-Dist: aiohttp (==3.8.1)
Requires-Dist: azure-storage-blob (==12.14.1)
Requires-Dist: pydantic (==1.9.0)
